pyRevealjs/__init__.py
pyRevealjs/presentation.py
pyRevealjs/presentation_settings.py
pyRevealjs/slide.py
pyRevealjs/slideGenerator.py
pyRevealjs/slide_catalog.py
pyRevealjs/slide_generator.py
pyRevealjs/slides.py
pyRevealjs/assets/firstPart.txt
pyRevealjs/assets/secondPart.txt
pyRevealjs/assets/template.html
pyRevealjs/assets/revealjsdist4.1.0/.gitignore
pyRevealjs/assets/revealjsdist4.1.0/.npmignore
pyRevealjs/assets/revealjsdist4.1.0/CONTRIBUTING.md
pyRevealjs/assets/revealjsdist4.1.0/README.md
pyRevealjs/assets/revealjsdist4.1.0/demo.html
pyRevealjs/assets/revealjsdist4.1.0/gulpfile.js
pyRevealjs/assets/revealjsdist4.1.0/index.html
pyRevealjs/assets/revealjsdist4.1.0/package-lock.json
pyRevealjs/assets/revealjsdist4.1.0/package.json
pyRevealjs/assets/revealjsdist4.1.0/.github/FUNDING.yml
pyRevealjs/assets/revealjsdist4.1.0/.github/workflows/js.yml
pyRevealjs/assets/revealjsdist4.1.0/css/layout.scss
pyRevealjs/assets/revealjsdist4.1.0/css/reveal.scss
pyRevealjs/assets/revealjsdist4.1.0/css/print/paper.scss
pyRevealjs/assets/revealjsdist4.1.0/css/print/pdf.scss
pyRevealjs/assets/revealjsdist4.1.0/css/theme/README.md
pyRevealjs/assets/revealjsdist4.1.0/css/theme/source/beige.scss
pyRevealjs/assets/revealjsdist4.1.0/css/theme/source/black.scss
pyRevealjs/assets/revealjsdist4.1.0/css/theme/source/blood.scss
pyRevealjs/assets/revealjsdist4.1.0/css/theme/source/league.scss
pyRevealjs/assets/revealjsdist4.1.0/css/theme/source/moon.scss
pyRevealjs/assets/revealjsdist4.1.0/css/theme/source/night.scss
pyRevealjs/assets/revealjsdist4.1.0/css/theme/source/serif.scss
pyRevealjs/assets/revealjsdist4.1.0/css/theme/source/simple.scss
pyRevealjs/assets/revealjsdist4.1.0/css/theme/source/sky.scss
pyRevealjs/assets/revealjsdist4.1.0/css/theme/source/solarized.scss
pyRevealjs/assets/revealjsdist4.1.0/css/theme/source/white.scss
pyRevealjs/assets/revealjsdist4.1.0/css/theme/template/exposer.scss
pyRevealjs/assets/revealjsdist4.1.0/css/theme/template/mixins.scss
pyRevealjs-2.6.dist-info/LICENSE
pyRevealjs-2.6.dist-info/METADATA
pyRevealjs-2.6.dist-info/WHEEL
pyRevealjs-2.6.dist-info/top_level.txt
pyRevealjs-2.6.dist-info/RECORD
