Metadata-Version: 2.1
Name: pyRevealjs
Version: 2.6
Summary: revealjs based presentation
Home-page: https://github.com/20centcroak/pyRevealjs
Author: 20centCroak
Author-email: 
License: UNKNOWN
Platform: UNKNOWN
Classifier: Programming Language :: Python :: 3
Classifier: License :: OSI Approved :: MIT License
Classifier: Operating System :: OS Independent
Requires-Python: >=3.6
Requires-Dist: BeautifulSoup4
